gssurgo/__init__.py
gssurgo/aoi.py
gssurgo/build_gpkg.py
gssurgo/gssurgo.py
gssurgo/query_gpkg.py
gssurgo/states.gpkg
gssurgo/viz_numeric_output.py
gssurgo-1.0.1.data/scripts/extract_gssurgo_tif
gssurgo-1.0.1.dist-info/LICENSE
gssurgo-1.0.1.dist-info/METADATA
gssurgo-1.0.1.dist-info/WHEEL
gssurgo-1.0.1.dist-info/top_level.txt
gssurgo-1.0.1.dist-info/RECORD
