Metadata-Version: 2.1
Name: gssurgo
Version: 1.0.1
Summary: Python toolbox enabling an open source gSSURGO workflow
Home-page: https://github.com/jsta/gssurgo
Author: Jemma Stachelek
Author-email: stachel2@msu.edu
License: UNKNOWN
Platform: UNKNOWN
Classifier: Programming Language :: Python :: 3
Classifier: License :: OSI Approved :: MIT License
Classifier: Operating System :: OS Independent
